{"Groups":[{"Gname":"PHYSIS","Sessions":[{"Id":{"Gid":0,"Sid":0},"Name":"docker","Host":"www.physis.kr","Port":"20022","User":"lannerkr","Pwd":null,"KeyPath":"/home/lannerkr/.ssh/id_rsa","Usepwd":false},{"Id":{"Gid":0,"Sid":1},"Name":"ubuntu151","Host":"www.physis.kr","Port":"20021","User":"physis","Pwd":null,"KeyPath":"/home/lannerkr/.ssh/id_rsa","Usepwd":false},{"Id":{"Gid":0,"Sid":2},"Name":"ubuntu1512","Host":"www.physis.kr","Port":"20021","User":"lannerkr","Pwd":null,"KeyPath":"/home/lannerkr/.ssh/id_rsa","Usepwd":false},{"Id":{"Gid":0,"Sid":3},"Name":"ubuntu1513","Host":"www.physis.kr","Port":"20021","User":"lannerkr","Pwd":null,"KeyPath":"/home/lannerkr/.ssh/id_rsa","Usepwd":false}]},{"Gname":"OCI","Sessions":[{"Id":{"Gid":1,"Sid":0},"Name":"oci","Host":"oci.physis.mooo.com","Port":"22","User":"lannerkr","Pwd":"17xIIhaA7StNjkq2SFBk5NhM6lo=","KeyPath":"/home/lannerkr/.ssh/id_rsa","Usepwd":false},{"Id":{"Gid":1,"Sid":1},"Name":"oca","Host":"oca.physis.mooo.com","Port":"22","User":"lannerkr","Pwd":"///6x4eiQp5HSMo+a1PqFU0/IhM=","KeyPath":"/home/lannerkr/.ssh/id_rsa","Usepwd":false}]}]}